url_filter/__init__.py
url_filter/constants.py
url_filter/exceptions.py
url_filter/fields.py
url_filter/filters.py
url_filter/utils.py
url_filter/validators.py
url_filter/backends/__init__.py
url_filter/backends/base.py
url_filter/backends/django.py
url_filter/backends/plain.py
url_filter/backends/sqlalchemy.py
url_filter/filtersets/__init__.py
url_filter/filtersets/base.py
url_filter/filtersets/django.py
url_filter/filtersets/plain.py
url_filter/filtersets/sqlalchemy.py
url_filter/integrations/__init__.py
url_filter/integrations/drf.py
url_filter/integrations/drf_coreapi.py
suap_duf-0.3.16.dist-info/AUTHORS.rst
suap_duf-0.3.16.dist-info/LICENSE.rst
suap_duf-0.3.16.dist-info/METADATA
suap_duf-0.3.16.dist-info/WHEEL
suap_duf-0.3.16.dist-info/top_level.txt
suap_duf-0.3.16.dist-info/RECORD
