Metadata-Version: 2.1
Name: suap-duf
Version: 0.3.16
Summary: Django URL Filter provides a safe way to filter data via human-friendly URLs.
Home-page: https://github.com/miki725/django-url-filter
Author: Miroslav Shubernetskiy
License: MIT
Keywords: django django-rest-framework
Platform: UNKNOWN
Classifier: Intended Audience :: Developers
Classifier: Natural Language :: English
Classifier: License :: OSI Approved :: MIT License
Classifier: Programming Language :: Python
Classifier: Programming Language :: Python :: 2.7
Classifier: Programming Language :: Python :: 3
Classifier: Programming Language :: Python :: 3.10
Classifier: Development Status :: 2 - Pre-Alpha
License-File: LICENSE.rst
License-File: AUTHORS.rst
Requires-Dist: cached-property
Requires-Dist: Django (>=1.8)
Requires-Dist: enum-compat
Requires-Dist: six
Requires-Dist: setuptools
